setup.py
schizophrenia/__init__.py
schizophrenia/manager.py
schizophrenia/result.py
schizophrenia/task.py
schizophrenia.egg-info/PKG-INFO
schizophrenia.egg-info/SOURCES.txt
schizophrenia.egg-info/dependency_links.txt
schizophrenia.egg-info/top_level.txt