Metadata-Version: 1.2
Name: schizophrenia
Version: 0.2.2
Summary: A task-based threading library based on Python threads.
Home-page: https://github.com/frank2/schizophrenia
Author: frank2
Author-email: frank2@dc949.org
License: GPLv3
Keywords: threading
Platform: UNKNOWN
Classifier: Development Status :: 4 - Beta
Classifier: Topic :: Software Development :: Libraries
Classifier: License :: OSI Approved :: GNU General Public License v3 (GPLv3)
Requires-Python: >=3
